{"pageContext":{"isCreatedByStatefulCreatePages":false,"bill":{"id":"a5a05d4e-7e36-11e9-862b-0242ac120002","session":"2019","identifier":"HB 346","title":"Revise election laws regarding privacy of voter information","subjects":["Documents","Elections  (see also: Ballot Issues)","Information Technology  (see also: Communications)"],"actions":[{"date":"2018-11-16","description":"Draft Request Received","chamber":"Staff","committee":"Staff","vote":null},{"date":"2019-01-02","description":"Draft On Hold","chamber":"Staff","committee":"Staff","vote":null},{"date":"2019-01-14","description":"Draft Taken Off Hold","chamber":"Staff","committee":"Staff","vote":null},{"date":"2019-01-19","description":"Draft to Requester for Review","chamber":"Staff","committee":"Staff","vote":null},{"date":"2019-01-22","description":"Draft to Requester for Review","chamber":"Staff","committee":"Staff","vote":null},{"date":"2019-01-23","description":"Draft in Legal Review","chamber":"Staff","committee":"Staff","vote":null},{"date":"2019-01-23","description":"Draft in Edit","chamber":"Staff","committee":"Staff","vote":null},{"date":"2019-01-24","description":"Draft to Drafter - Edit Review [SMH]","chamber":"Staff","committee":"Staff","vote":null},{"date":"2019-01-24","description":"Draft in Input/Proofing","chamber":"Staff","committee":"Staff","vote":null},{"date":"2019-01-24","description":"Draft in Final Drafter Review","chamber":"Staff","committee":"Staff","vote":null},{"date":"2019-01-24","description":"Bill Draft Text Available Electronically","chamber":"Staff","committee":"Staff","vote":null},{"date":"2019-01-24","description":"Executive Director Review","chamber":"Staff","committee":"Staff","vote":null},{"date":"2019-01-24","description":"Draft in Assembly","chamber":"Staff","committee":"Staff","vote":null},{"date":"2019-01-25","description":"Executive Director Final Review","chamber":"Staff","committee":"Staff","vote":null},{"date":"2019-01-25","description":"Draft Ready for Delivery","chamber":"Staff","committee":"Staff","vote":null},{"date":"2019-01-28","description":"Draft Delivered to Requester","chamber":"Staff","committee":"Staff","vote":null},{"date":"2019-01-31","description":"Introduced","chamber":"House","committee":"House","vote":null},{"date":"2019-01-31","description":"Referred to Committee","chamber":"House","committee":"(H) State Administration","vote":null},{"date":"2019-01-31","description":"First Reading","chamber":"House","committee":"(H) State Administration","vote":null},{"date":"2019-01-31","description":"Introduced Bill Text Available Electronically","chamber":"Staff","committee":"Staff","vote":null},{"date":"2019-02-11","description":"Hearing Canceled","chamber":"House","committee":"(H) State Administration","vote":null},{"date":"2019-02-11","description":"Bill Withdrawn per House Rule H30-50(3)(b)","chamber":"House","committee":"House","vote":null},{"date":"2019-03-01","description":"Missed Deadline for General Bill Transmittal","chamber":"House","committee":"House","vote":null},{"date":"2019-04-25","description":"Died in Process","chamber":"House","committee":"House","vote":null}],"sponsor":"Mary Ann Dunwell","sponsorParty":"D","requestor":"Dunwell","source":"http://laws.leg.mt.gov/legprd/LAW0210W$BSIV.ActionQuery?P_BILL_NO1=346&P_BLTP_BILL_TYP_CD=HB&Z_ACTION=Find&P_SESS=20191","textUrl":"http://leg.mt.gov/bills/2019/billpdf/HB0346.pdf","textType":"introduced","vetoMemoUrl":null,"status":"Probably Dead"}}}